flask_opa.py
Flask_OPA-1.0.0.dist-info/LICENSE.md
Flask_OPA-1.0.0.dist-info/METADATA
Flask_OPA-1.0.0.dist-info/WHEEL
Flask_OPA-1.0.0.dist-info/top_level.txt
Flask_OPA-1.0.0.dist-info/RECORD
