Metadata-Version: 2.1
Name: Flask-OPA
Version: 1.0.0
Summary: Flask extension to use OPA as a client
Home-page: https://github.com/EliuX/Flask-OPA
Author: Eliecer Hernandez Garbey
Author-email: eliecerhdz@gmail.com
License: MIT
Project-URL: Bug Tracker, https://github.com/EliuX/Flask-OPA/issues
Project-URL: Source Code, https://github.com/EliuX/Flask-OPA
Platform: UNKNOWN
Classifier: Environment :: Web Environment
Classifier: Intended Audience :: Developers
Classifier: License :: OSI Approved :: MIT License
Classifier: Operating System :: OS Independent
Classifier: Programming Language :: Python
Classifier: Topic :: Internet :: WWW/HTTP :: Dynamic Content
Classifier: Topic :: Software Development :: Libraries :: Python Modules
Classifier: Topic :: System :: Systems Administration :: Authentication/Directory
Requires-Dist: Flask
Requires-Dist: requests
